shared_ds/__init__.py
shared_ds/shared_array.py
shared_ds/shared_bytes_io.py
shared_ds-0.0.5.dist-info/METADATA
shared_ds-0.0.5.dist-info/WHEEL
shared_ds-0.0.5.dist-info/top_level.txt
shared_ds-0.0.5.dist-info/RECORD
