Metadata-Version: 2.1
Name: shared-ds
Version: 0.0.5
Summary: Provide shared memory data structures!
Home-page: https://github.com/PicsArt/shared-data-structures
Author: Vigen Sahakyan
Author-email: vigen.sahakyan@picsart.com
License: MIT
Platform: Linux
Platform: Mac OS-X
Platform: Unix
Requires-Dist: numpy (>=1.16.4)
Requires-Dist: posix-ipc (>=1.0.4)
